{
  "AbilityScore": "Dexterity",
  "Modifiers": [
    {
      "ReactionAdjustment": -6,
      "MissileAttackAdjustment": -6,
      "DefensiveAdjustment": 5
    },
    {
      "ReactionAdjustment": -4,
      "MissileAttackAdjustment": -4,
      "DefensiveAdjustment": 5
    },
    {
      "ReactionAdjustment": -3,
      "MissileAttackAdjustment": -3,
      "DefensiveAdjustment": 4
    },
    {
      "ReactionAdjustment": -2,
      "MissileAttackAdjustment": -2,
      "DefensiveAdjustment": 3
    },
    {
      "ReactionAdjustment": -1,
      "MissileAttackAdjustment": -1,
      "DefensiveAdjustment": 2
    },
    {
      "ReactionAdjustment": 0,
      "MissileAttackAdjustment": 0,
      "DefensiveAdjustment": 1
    },
    {
      "ReactionAdjustment": 0,
      "MissileAttackAdjustment": 0,
      "DefensiveAdjustment": 0
    },
    {
      "ReactionAdjustment": 0,
      "MissileAttackAdjustment": 0,
      "DefensiveAdjustment": 0
    },
    {
      "ReactionAdjustment": 0,
      "MissileAttackAdjustment": 0,
      "DefensiveAdjustment": 0
    },
    {
      "ReactionAdjustment": 0,
      "MissileAttackAdjustment": 0,
      "DefensiveAdjustment": 0
    },
    {
      "ReactionAdjustment": 0,
      "MissileAttackAdjustment": 0,
      "DefensiveAdjustment": 0
    },
    {
      "ReactionAdjustment": 0,
      "MissileAttackAdjustment": 0,
      "DefensiveAdjustment": 0
    },
    {
      "ReactionAdjustment": 0,
      "MissileAttackAdjustment": 0,
      "DefensiveAdjustment": 0
    },
    {
      "ReactionAdjustment": 0,
      "MissileAttackAdjustment": 0,
      "DefensiveAdjustment": 0
    },
    {
      "ReactionAdjustment": 0,
      "MissileAttackAdjustment": 0,
      "DefensiveAdjustment": -1
    },
    {
      "ReactionAdjustment": 1,
      "MissileAttackAdjustment": 1,
      "DefensiveAdjustment": -2
    },
    {
      "ReactionAdjustment": 2,
      "MissileAttackAdjustment": 2,
      "DefensiveAdjustment": -3
    },
    {
      "ReactionAdjustment": 2,
      "MissileAttackAdjustment": 2,
      "DefensiveAdjustment": -3
    },
    {
      "ReactionAdjustment": 2,
      "MissileAttackAdjustment": 2,
      "DefensiveAdjustment": -3
    },
    {
      "ReactionAdjustment": 3,
      "MissileAttackAdjustment": 3,
      "DefensiveAdjustment": -4
    },
    {
      "ReactionAdjustment": 4,
      "MissileAttackAdjustment": 4,
      "DefensiveAdjustment": -5
    },
    {
      "ReactionAdjustment": 4,
      "MissileAttackAdjustment": 4,
      "DefensiveAdjustment": -5
    },
    {
      "ReactionAdjustment": 4,
      "MissileAttackAdjustment": 4,
      "DefensiveAdjustment": -5
    },
    {
      "ReactionAdjustment": 5,
      "MissileAttackAdjustment": 5,
      "DefensiveAdjustment": -6
    },
    {
      "ReactionAdjustment": 5,
      "MissileAttackAdjustment": 5,
      "DefensiveAdjustment": -6
    }
  ]
}